{"id":26,"code_display":"H3","code_normalized":"H3","indication_type":"remote_controller","unit_scope":"outdoor","short_label":"Sistema del presostato de alta","aliases":[{"alias_display":"H3","alias_normalized":"H3"}],"tags":["alta","entrada","esperado","estado","presenta","presostato","sistema"],"interpretations":[{"id":19,"title":"Sistema del presostato de alta","description":"La entrada del presostato de alta no presenta el estado esperado.","source_kind":"official","confidence":"high","review_status":"reviewed","info_items":[{"id":1901,"item_type":"machine_behavior","title":null,"body":"La unidad impide el funcionamiento del compresor mientras la cadena de alta no sea segura.","sort_order":1,"review_status":"reviewed","origin_ref":"ESiES06-07"},{"id":1902,"item_type":"related_element","title":null,"body":"Sistema del presostato de alta","sort_order":2,"review_status":"reviewed","origin_ref":"ESiES06-07"},{"id":1903,"item_type":"cause","title":null,"body":"Presostato activado","sort_order":3,"review_status":"reviewed","origin_ref":"ESiES06-07"},{"id":1904,"item_type":"cause","title":null,"body":"Cableado o conector abierto","sort_order":4,"review_status":"reviewed","origin_ref":"ESiES06-07"},{"id":1905,"item_type":"cause","title":null,"body":"Presostato defectuoso","sort_order":5,"review_status":"reviewed","origin_ref":"ESiES06-07"},{"id":1906,"item_type":"cause","title":null,"body":"Presión realmente alta","sort_order":6,"review_status":"reviewed","origin_ref":"ESiES06-07"},{"id":1907,"item_type":"check","title":null,"body":"Medir presión antes de puentear o sustituir componentes","sort_order":7,"review_status":"reviewed","origin_ref":"ESiES06-07"},{"id":1908,"item_type":"check","title":null,"body":"Comprobar continuidad con alimentación desconectada","sort_order":8,"review_status":"reviewed","origin_ref":"ESiES06-07"},{"id":1909,"item_type":"check","title":null,"body":"Revisar circuito frigorífico","sort_order":9,"review_status":"reviewed","origin_ref":"ESiES06-07"},{"id":1910,"item_type":"observation","title":null,"body":"Variante documentada en ESiES06-07; el mismo código puede tener otro significado en otra familia Daikin.","sort_order":10,"review_status":"reviewed","origin_ref":"ESiES06-07"}],"operational_impacts":[{"stop_level":"protected_stop","summary":"La unidad impide el funcionamiento del compresor mientras la cadena de alta no sea segura.","affected_scope":"La unidad, módulo o sistema descrito por esta variante documental.","unaffected_scope":null,"restart_behavior":"Corregir la causa y seguir el rearme o la repetición de prueba indicados por el manual.","degraded_behavior":null,"notes":"No se generaliza el alcance a otras familias Daikin."}],"datasets":[],"sources":[{"title":"Manual de servicio — Daikin Sky Air RZQS71~125B7V3B","document_ref":"ESiES06-07","source_url":null,"page_start":"3-73","page_end":"3-73","section":"Detección de averías — H3: Sistema del presostato de alta"}]}],"media":[]}
