{"id":41,"code_display":"L5","code_normalized":"L5","indication_type":"remote_controller","unit_scope":"outdoor","short_label":"2 interpretaciones documentadas","aliases":[{"alias_display":"L5","alias_normalized":"L5"}],"tags":["corriente","detecta","excesiva","instantanea","inverter","limite","modulo","multisplit","potencia","salida","sobrecorriente","supera"],"interpretations":[{"id":27,"title":"Sobrecorriente instantánea del inverter","description":"El módulo de potencia detecta una corriente de salida excesiva.","source_kind":"official","confidence":"high","review_status":"reviewed","info_items":[{"id":2701,"item_type":"machine_behavior","title":null,"body":"El inverter corta inmediatamente la salida al compresor.","sort_order":1,"review_status":"reviewed","origin_ref":"ESiES06-07"},{"id":2702,"item_type":"related_element","title":null,"body":"Sobrecorriente instantánea del inverter","sort_order":2,"review_status":"reviewed","origin_ref":"ESiES06-07"},{"id":2703,"item_type":"cause","title":null,"body":"Compresor bloqueado o defectuoso","sort_order":3,"review_status":"reviewed","origin_ref":"ESiES06-07"},{"id":2704,"item_type":"cause","title":null,"body":"Cableado U/V/W anómalo","sort_order":4,"review_status":"reviewed","origin_ref":"ESiES06-07"},{"id":2705,"item_type":"cause","title":null,"body":"Módulo inverter defectuoso","sort_order":5,"review_status":"reviewed","origin_ref":"ESiES06-07"},{"id":2706,"item_type":"cause","title":null,"body":"Presión diferencial excesiva","sort_order":6,"review_status":"reviewed","origin_ref":"ESiES06-07"},{"id":2707,"item_type":"check","title":null,"body":"Revisar cableado y bobinados con alimentación desconectada","sort_order":7,"review_status":"reviewed","origin_ref":"ESiES06-07"},{"id":2708,"item_type":"check","title":null,"body":"Comprobar condiciones de arranque","sort_order":8,"review_status":"reviewed","origin_ref":"ESiES06-07"},{"id":2709,"item_type":"check","title":null,"body":"Seguir la prueba de módulo de potencia","sort_order":9,"review_status":"reviewed","origin_ref":"ESiES06-07"},{"id":2710,"item_type":"observation","title":null,"body":"Variante documentada en ESiES06-07; el mismo código puede tener otro significado en otra familia Daikin.","sort_order":10,"review_status":"reviewed","origin_ref":"ESiES06-07"}],"operational_impacts":[{"stop_level":"protected_stop","summary":"El inverter corta inmediatamente la salida al compresor.","affected_scope":"La unidad, módulo o sistema descrito por esta variante documental.","unaffected_scope":null,"restart_behavior":"Corregir la causa y seguir el rearme o la repetición de prueba indicados por el manual.","degraded_behavior":null,"notes":"No se generaliza el alcance a otras familias Daikin."}],"datasets":[],"sources":[{"title":"Manual de servicio — Daikin Sky Air RZQS71~125B7V3B","document_ref":"ESiES06-07","source_url":null,"page_start":"3-80","page_end":"3-80","section":"Detección de averías — L5: Sobrecorriente instantánea del inverter"}]},{"id":77,"title":"Sobrecorriente de salida — multisplit","description":"La corriente de salida del inverter supera el límite.","source_kind":"official","confidence":"high","review_status":"reviewed","info_items":[{"id":7701,"item_type":"machine_behavior","title":null,"body":"La salida se corta inmediatamente.","sort_order":1,"review_status":"reviewed","origin_ref":"SiUS121602E"},{"id":7702,"item_type":"related_element","title":null,"body":"Sobrecorriente de salida — multisplit","sort_order":2,"review_status":"reviewed","origin_ref":"SiUS121602E"},{"id":7703,"item_type":"cause","title":null,"body":"Compresor bloqueado","sort_order":3,"review_status":"reviewed","origin_ref":"SiUS121602E"},{"id":7704,"item_type":"cause","title":null,"body":"Cableado U/V/W","sort_order":4,"review_status":"reviewed","origin_ref":"SiUS121602E"},{"id":7705,"item_type":"cause","title":null,"body":"Módulo defectuoso","sort_order":5,"review_status":"reviewed","origin_ref":"SiUS121602E"},{"id":7706,"item_type":"check","title":null,"body":"Revisar cableado y compresor","sort_order":6,"review_status":"reviewed","origin_ref":"SiUS121602E"},{"id":7707,"item_type":"check","title":null,"body":"Seguir prueba de módulo","sort_order":7,"review_status":"reviewed","origin_ref":"SiUS121602E"},{"id":7708,"item_type":"observation","title":null,"body":"Variante documentada en SiUS121602E; el mismo código puede tener otro significado en otra familia Daikin.","sort_order":8,"review_status":"reviewed","origin_ref":"SiUS121602E"}],"operational_impacts":[{"stop_level":"protected_stop","summary":"La salida se corta inmediatamente.","affected_scope":"La unidad, módulo o sistema descrito por esta variante documental.","unaffected_scope":null,"restart_behavior":"Corregir la causa y seguir el rearme o la repetición de prueba indicados por el manual.","degraded_behavior":null,"notes":"No se generaliza el alcance a otras familias Daikin."}],"datasets":[],"sources":[{"title":"Manual de servicio — Daikin Multi-Split 2MXL/3MXL-Q","document_ref":"SiUS121602E","source_url":null,"page_start":"162","page_end":"162","section":"Service Diagnosis — L5: Sobrecorriente de salida — multisplit"}]}],"media":[]}
