{"id":31,"code_display":"E: A3","code_normalized":"EA3","indication_type":"remote_controller","unit_scope":"outdoor","short_label":"Protección por temperatura elevada del compresor","aliases":[{"alias_display":"EA3","alias_normalized":"EA3"},{"alias_display":"A3","alias_normalized":"A3"},{"alias_display":"10 parpadeos OPERATION + 3 parpadeos TIMER","alias_normalized":"10PARPADEOSOPERATION3PARPADEOSTIMER"}],"tags":[],"interpretations":[{"id":79,"title":"Protección por temperatura del compresor","description":"Temperatura del compresor anormal.","source_kind":"official","confidence":"high","review_status":"reviewed","info_items":[],"operational_impacts":[],"datasets":[],"sources":[{"title":"Service Manual — Fujitsu/General ABYG45LRTA / AOYG45LETL","document_ref":"ABYG45LRTA_AOYG45LETL","source_url":"https://www.fujitsuklima.hu/vmfiles/attachments/sm/fj_sm_abyg45lrta_aoyg45letl.pdf","page_start":"15","page_end":"16","section":"Error detection"}]},{"id":31,"title":"Protección por temperatura elevada del compresor","description":"Se producen 2 paradas en 24 horas porque la temperatura del compresor alcanza o supera 108 °C.","source_kind":"official","confidence":"high","review_status":"reviewed","info_items":[{"id":319,"item_type":"cause","title":null,"body":"Válvula de servicio cerrada.","sort_order":5,"review_status":"reviewed"},{"id":320,"item_type":"cause","title":null,"body":"EEV defectuosa o filtro obstruido.","sort_order":6,"review_status":"reviewed"},{"id":321,"item_type":"cause","title":null,"body":"Ventilación exterior deficiente o intercambiador sucio.","sort_order":7,"review_status":"reviewed"},{"id":322,"item_type":"cause","title":null,"body":"Sonda de compresor defectuosa.","sort_order":8,"review_status":"reviewed"},{"id":323,"item_type":"cause","title":null,"body":"Falta de refrigerante.","sort_order":9,"review_status":"reviewed"},{"id":324,"item_type":"cause","title":null,"body":"Fallo de la PCB principal.","sort_order":10,"review_status":"reviewed"},{"id":325,"item_type":"check","title":null,"body":"Comprobar válvulas de servicio.","sort_order":11,"review_status":"reviewed"},{"id":326,"item_type":"check","title":null,"body":"Comprobar EEV y obstrucciones.","sort_order":12,"review_status":"reviewed"},{"id":327,"item_type":"check","title":null,"body":"Comprobar ventilador y limpieza del intercambiador.","sort_order":13,"review_status":"reviewed"},{"id":328,"item_type":"check","title":null,"body":"Medir la sonda de temperatura del compresor.","sort_order":14,"review_status":"reviewed"},{"id":329,"item_type":"check","title":null,"body":"Comprobar fugas y cantidad de refrigerante.","sort_order":15,"review_status":"reviewed"},{"id":330,"item_type":"check","title":null,"body":"Si todo es correcto, sustituir la PCB principal.","sort_order":16,"review_status":"reviewed"},{"id":331,"item_type":"observation","title":null,"body":"El manual no aporta en la tabla general una curva identificada expresamente para esta sonda; no se asigna una curva por inferencia.","sort_order":17,"review_status":"reviewed"},{"id":315,"item_type":"related_element","title":null,"body":"Sonda de temperatura del compresor","sort_order":1,"review_status":"reviewed"},{"id":316,"item_type":"related_element","title":null,"body":"EEV","sort_order":2,"review_status":"reviewed"},{"id":317,"item_type":"related_element","title":null,"body":"Circuito frigorífico","sort_order":3,"review_status":"reviewed"},{"id":318,"item_type":"related_element","title":null,"body":"Ventilador y batería exterior","sort_order":4,"review_status":"reviewed"}],"operational_impacts":[],"datasets":[],"sources":[{"title":"Service Manual — Fujitsu/General AOEG22KATA","document_ref":"AOEG22KATA","source_url":"https://webstore.uk.fujitsu-general.com/product/attachment/AOEG22KATA/service%20manual.pdf","page_start":"03-39","page_end":"03-40","section":"2. Troubleshooting with error code"}]}],"media":[]}