{"id":59,"code_display":"Ed","code_normalized":"ED","indication_type":"display_led_or_controller","unit_scope":"outdoor","short_label":"Comunicación serie entre placa de control y placa de potencia — variante CITY MULTI 0403","aliases":[{"alias_display":"0403","alias_normalized":"0403"},{"alias_display":"Ed","alias_normalized":"ED"}],"tags":["0403","city","completo","comunicacion","control","corresponde","corto","display","entre","esta","familia","multi","placa","potencia","serie","subcodigo","variante"],"interpretations":[{"id":46,"title":"Comunicación serie entre placa de control y placa de potencia — variante CITY MULTI 0403","description":"El display corto Ed corresponde al subcódigo completo 0403 en esta familia.","source_kind":"official","confidence":"high","review_status":"reviewed","info_items":[{"id":4601,"item_type":"machine_behavior","title":null,"body":"La unidad exterior detiene su funcionamiento.","sort_order":1,"review_status":"reviewed","origin_ref":"OCH675E"},{"id":4602,"item_type":"related_element","title":null,"body":"Comunicación serie entre placa de control y placa de potencia — variante CITY MULTI 0403","sort_order":2,"review_status":"reviewed","origin_ref":"OCH675E"},{"id":4603,"item_type":"cause","title":null,"body":"Conector entre placas o PCB defectuosa","sort_order":3,"review_status":"reviewed","origin_ref":"OCH675E"},{"id":4604,"item_type":"check","title":null,"body":"Revisar conectores y alimentaciones con tensión cortada","sort_order":4,"review_status":"reviewed","origin_ref":"OCH675E"},{"id":4605,"item_type":"observation","title":null,"body":"Variante documentada en OCH675E. Confirme familia, forma de indicación y subcódigo antes de aplicar la prueba.","sort_order":5,"review_status":"reviewed","origin_ref":"OCH675E"}],"operational_impacts":[{"stop_level":"protected_stop","summary":"La unidad exterior detiene su funcionamiento.","affected_scope":"El alcance indicado para esta familia documental.","unaffected_scope":null,"restart_behavior":"Corregir la causa y aplicar el rearme o repetición de prueba descritos en el manual.","degraded_behavior":null,"notes":"No se generaliza este comportamiento a otra familia Mitsubishi Electric."}],"datasets":[],"sources":[{"title":"Manual de servicio — PUMY-P200YKM2","document_ref":"OCH675E","source_url":"https://library.mitsubishielectric.co.uk/pdf/download_full/4401","page_start":"43","page_end":"43","section":"Diagnóstico — Ed: Comunicación serie entre placa de control y placa de potencia — variante CITY MULTI 0403"}]}],"media":[]}
