{"id":62,"code_display":"F3","code_normalized":"F3","indication_type":"display_led_or_controller","unit_scope":"outdoor","short_label":"2 interpretaciones documentadas","aliases":[{"alias_display":"5202","alias_normalized":"5202"},{"alias_display":"F3","alias_normalized":"F3"}],"tags":["5202","63ls","aceptado","anormal","baja","city","completo","corresponde","corto","display","esta","familia","fuera","multi","presion","rango","senal","sensor"],"interpretations":[{"id":28,"title":"Sensor de baja presión anormal","description":"La señal de baja presión está fuera del rango aceptado.","source_kind":"official","confidence":"high","review_status":"reviewed","info_items":[{"id":2801,"item_type":"machine_behavior","title":null,"body":"La exterior detiene o limita el compresor.","sort_order":1,"review_status":"reviewed","origin_ref":"OCH832B"},{"id":2802,"item_type":"related_element","title":null,"body":"Sensor de baja presión anormal","sort_order":2,"review_status":"reviewed","origin_ref":"OCH832B"},{"id":2803,"item_type":"cause","title":null,"body":"Sensor defectuoso","sort_order":3,"review_status":"reviewed","origin_ref":"OCH832B"},{"id":2804,"item_type":"cause","title":null,"body":"Conector abierto","sort_order":4,"review_status":"reviewed","origin_ref":"OCH832B"},{"id":2805,"item_type":"cause","title":null,"body":"Presión realmente fuera de rango","sort_order":5,"review_status":"reviewed","origin_ref":"OCH832B"},{"id":2806,"item_type":"cause","title":null,"body":"PCB defectuosa","sort_order":6,"review_status":"reviewed","origin_ref":"OCH832B"},{"id":2807,"item_type":"check","title":null,"body":"Comparar presión real con lectura de monitor","sort_order":7,"review_status":"reviewed","origin_ref":"OCH832B"},{"id":2808,"item_type":"check","title":null,"body":"Revisar sensor y cableado","sort_order":8,"review_status":"reviewed","origin_ref":"OCH832B"},{"id":2809,"item_type":"observation","title":null,"body":"Variante documentada en OCH832B. Confirme familia, forma de indicación y subcódigo antes de aplicar la prueba.","sort_order":9,"review_status":"reviewed","origin_ref":"OCH832B"}],"operational_impacts":[{"stop_level":"warning","summary":"La exterior detiene o limita el compresor.","affected_scope":"El alcance indicado para esta familia documental.","unaffected_scope":null,"restart_behavior":"Corregir la causa y aplicar el rearme o repetición de prueba descritos en el manual.","degraded_behavior":null,"notes":"No se generaliza este comportamiento a otra familia Mitsubishi Electric."}],"datasets":[],"sources":[{"title":"Manual de servicio — PUZ-ZM100/125/140V(Y)DA","document_ref":"OCH832B","source_url":"https://library.mitsubishielectric.co.uk/pdf/download_full/5247","page_start":"67","page_end":"67","section":"Diagnóstico — F3: Sensor de baja presión anormal"}]},{"id":88,"title":"Sensor de baja presión 63LS — variante CITY MULTI 5202","description":"El display corto F3 corresponde al subcódigo completo 5202 en esta familia.","source_kind":"official","confidence":"high","review_status":"reviewed","info_items":[{"id":8801,"item_type":"machine_behavior","title":null,"body":"El compresor se protege.","sort_order":1,"review_status":"reviewed","origin_ref":"OCH675E"},{"id":8802,"item_type":"related_element","title":null,"body":"Sensor de baja presión 63LS — variante CITY MULTI 5202","sort_order":2,"review_status":"reviewed","origin_ref":"OCH675E"},{"id":8803,"item_type":"cause","title":null,"body":"Señal de baja fuera de rango, sensor o cable","sort_order":3,"review_status":"reviewed","origin_ref":"OCH675E"},{"id":8804,"item_type":"check","title":null,"body":"Comparar presión real con monitor y revisar sensor","sort_order":4,"review_status":"reviewed","origin_ref":"OCH675E"},{"id":8805,"item_type":"observation","title":null,"body":"Variante documentada en OCH675E. Confirme familia, forma de indicación y subcódigo antes de aplicar la prueba.","sort_order":5,"review_status":"reviewed","origin_ref":"OCH675E"}],"operational_impacts":[{"stop_level":"protected_stop","summary":"El compresor se protege.","affected_scope":"El alcance indicado para esta familia documental.","unaffected_scope":null,"restart_behavior":"Corregir la causa y aplicar el rearme o repetición de prueba descritos en el manual.","degraded_behavior":null,"notes":"No se generaliza este comportamiento a otra familia Mitsubishi Electric."}],"datasets":[],"sources":[{"title":"Manual de servicio — PUMY-P200YKM2","document_ref":"OCH675E","source_url":"https://library.mitsubishielectric.co.uk/pdf/download_full/4401","page_start":"74","page_end":"74","section":"Diagnóstico — F3: Sensor de baja presión 63LS — variante CITY MULTI 5202"}]}],"media":[]}
